<?xml version="1.0" encoding="utf-8"?>
<xliff xmlns="urn:oasis:names:tc:xliff:document:1.2" xmlns:xsi="http://www.w3.org/2001/XMLSchema-instance" version="1.2" xsi:schemaLocation="urn:oasis:names:tc:xliff:document:1.2 xliff-core-1.2-transitional.xsd">
  <file datatype="xml" original="AddressHeader.xml" source-language="en-US" target-language="ko-KR">
    <header>
      <tool tool-id="mdxliff" tool-name="mdxliff" tool-version="1.0-15c36f0" tool-company="Microsoft" />
      <xliffext:skl_file_name xmlns:xliffext="urn:microsoft:content:schema:xliffextensions">02cd5861-7ce2-4a82-b358-31f8435a0ac508a15318f104b4ed23250e4cec7a35de84fc780a.skl</xliffext:skl_file_name>
      <xliffext:version xmlns:xliffext="urn:microsoft:content:schema:xliffextensions">1.2</xliffext:version>
      <xliffext:ms.openlocfilehash xmlns:xliffext="urn:microsoft:content:schema:xliffextensions">08a15318f104b4ed23250e4cec7a35de84fc780a</xliffext:ms.openlocfilehash>
      <xliffext:ms.sourcegitcommit xmlns:xliffext="urn:microsoft:content:schema:xliffextensions">d31dc2ede16f6f7bc64e90d9f897ff54c4e3869b</xliffext:ms.sourcegitcommit>
      <xliffext:ms.lasthandoff xmlns:xliffext="urn:microsoft:content:schema:xliffextensions">04/03/2018</xliffext:ms.lasthandoff>
      <xliffext:moniker_ids xmlns:xliffext="urn:microsoft:content:schema:xliffextensions">netcore-1.0,netcore-1.1,netcore-2.0,netframework-4.5.1,netframework-4.5.2,netframework-4.5,netframework-4.6.1,netframework-4.6.2,netframework-4.6,netframework-4.7.1,netframework-4.7,xamarinandroid-7.1,xamarinios-10.8,xamarinmac-3.0</xliffext:moniker_ids>
    </header>
    <body>
      <group id="content" extype="content">
        <trans-unit id="101" translate="yes" xml:space="preserve" uid="T:System.ServiceModel.Channels.AddressHeader">
          <source>Represents a header that encapsulates an address information item used to identify or interact with an endpoint.</source>
          <target state="translated">끝점을 확인하거나 상호 작용하는 데 사용되는 주소 정보 항목을 캡슐화하는 헤더를 나타냅니다.</target>       </trans-unit>
        <trans-unit id="102" translate="yes" xml:space="preserve" extradata="MT" uid="T:System.ServiceModel.Channels.AddressHeader">
          <source>An <ph id="ph1">&lt;xref:System.ServiceModel.Channels.AddressHeader&gt;</ph> is characterized by a name and namespace and has a value that contains optional information used to identify or interact with an endpoint.</source>
          <target state="translated"><ph id="ph1">&lt;xref:System.ServiceModel.Channels.AddressHeader&gt;</ph>의 특성은 이름과 네임스페이스로 지정되며 끝점을 확인하거나 상호 작용하는 데 사용되는 선택적 정보가 포함된 값을 가집니다.</target>       </trans-unit>
        <trans-unit id="103" translate="yes" xml:space="preserve" extradata="MT" uid="T:System.ServiceModel.Channels.AddressHeader">
          <source>The name can be accessed by the <ph id="ph1">&lt;xref:System.ServiceModel.Channels.AddressHeader.Name%2A&gt;</ph> property and the namespace by the <ph id="ph2">&lt;xref:System.ServiceModel.Channels.AddressHeader.Namespace%2A&gt;</ph> property.</source>
          <target state="translated"><ph id="ph1">&lt;xref:System.ServiceModel.Channels.AddressHeader.Name%2A&gt;</ph> 속성을 통해 이름에 액세스할 수 있고 <ph id="ph2">&lt;xref:System.ServiceModel.Channels.AddressHeader.Namespace%2A&gt;</ph> 속성을 통해 네임스페이스에 액세스할 수 있습니다.</target>       </trans-unit>
        <trans-unit id="104" translate="yes" xml:space="preserve" extradata="MT" uid="T:System.ServiceModel.Channels.AddressHeader">
          <source>The following example shows how to create address headers, access their properties, add them to a service endpoint and host the service using the endpoint.</source>
          <target state="translated">다음 예제에서는 주소 헤더 만들기, 주소 헤더 속성 액세스, 서비스 끝점에 주소 헤더 추가 및 끝점을 사용한 서비스 호스팅 방법을 보여 줍니다.</target>       </trans-unit>
        <trans-unit id="105" translate="yes" xml:space="preserve" uid="M:System.ServiceModel.Channels.AddressHeader.#ctor">
          <source>Initializes a new instance of the <ph id="ph1">&lt;see cref="T:System.ServiceModel.Channels.AddressHeader" /&gt;</ph> class.</source>
          <target state="translated"><ph id="ph1">&lt;see cref="T:System.ServiceModel.Channels.AddressHeader" /&gt;</ph> 클래스의 새 인스턴스를 초기화합니다.</target>       </trans-unit>
        <trans-unit id="106" translate="yes" xml:space="preserve" extradata="MT" uid="M:System.ServiceModel.Channels.AddressHeader.#ctor">
          <source>Use the <ph id="ph1">&lt;xref:System.ServiceModel.Channels.AddressHeader.CreateAddressHeader%2A&gt;</ph> to create new <ph id="ph2">&lt;xref:System.ServiceModel.Channels.AddressHeader&gt;</ph> objects.</source>
          <target state="translated"><ph id="ph1">&lt;xref:System.ServiceModel.Channels.AddressHeader.CreateAddressHeader%2A&gt;</ph>를 사용하여 새 <ph id="ph2">&lt;xref:System.ServiceModel.Channels.AddressHeader&gt;</ph> 개체를 만듭니다.</target>       </trans-unit>
        <trans-unit id="107" translate="yes" xml:space="preserve" uid="T:System.ServiceModel.Channels.AddressHeader">
          <source>Creates a new instance of the <ph id="ph1">&lt;see cref="T:System.ServiceModel.Channels.AddressHeader" /&gt;</ph> class.</source>
          <target state="translated">
          <ph id="ph1">&lt;see cref="T:System.ServiceModel.Channels.AddressHeader" /&gt;</ph> 클래스의 새 인스턴스를 만듭니다.</target>       </trans-unit>
        <trans-unit id="108" translate="yes" xml:space="preserve" extradata="MT" uid="T:System.ServiceModel.Channels.AddressHeader">
          <source>The object that contains the information item is serialized into the address header by an <ph id="ph1">&lt;xref:System.Runtime.Serialization.XmlObjectSerializer&gt;</ph> object.</source>
          <target state="translated">정보 항목이 포함된 개체는 <ph id="ph1">&lt;xref:System.Runtime.Serialization.XmlObjectSerializer&gt;</ph> 개체에 의해 주소 헤더로 serialize됩니다.</target>       </trans-unit>
        <trans-unit id="109" translate="yes" xml:space="preserve" uid="M:System.ServiceModel.Channels.AddressHeader.CreateAddressHeader(System.Object)">
          <source>The information item for the address header.</source>
          <target state="translated">주소 헤더의 정보 항목입니다.</target>       </trans-unit>
        <trans-unit id="110" translate="yes" xml:space="preserve" uid="M:System.ServiceModel.Channels.AddressHeader.CreateAddressHeader(System.Object)">
          <source>Creates a new instance of the <ph id="ph1">&lt;see cref="T:System.ServiceModel.Channels.AddressHeader" /&gt;</ph> class with a specified value.</source>
          <target state="translated">지정된 값을 사용하여 <ph id="ph1">&lt;see cref="T:System.ServiceModel.Channels.AddressHeader" /&gt;</ph> 클래스의 새 인스턴스를 만듭니다.</target>       </trans-unit>
        <trans-unit id="111" translate="yes" xml:space="preserve" uid="M:System.ServiceModel.Channels.AddressHeader.CreateAddressHeader(System.Object)">
          <source>The <ph id="ph1">&lt;see cref="T:System.ServiceModel.Channels.AddressHeader" /&gt;</ph> that contains the information item specified by the <ph id="ph2">&lt;paramref name="value" /&gt;</ph> parameter.</source>
          <target state="translated"><ph id="ph1">&lt;see cref="T:System.ServiceModel.Channels.AddressHeader" /&gt;</ph> 매개 변수에 의해 지정된 정보 항목을 포함하는 <ph id="ph2">&lt;paramref name="value" /&gt;</ph>입니다.</target>       </trans-unit>
        <trans-unit id="112" translate="yes" xml:space="preserve" extradata="MT" uid="M:System.ServiceModel.Channels.AddressHeader.CreateAddressHeader(System.Object)">
          <source>The following example shows how to create an address header using this method.</source>
          <target state="translated">@FSHO1@다음 예제에서는 이 메서드를 사용하여 주소 헤더를 만드는 방법을 보여 줍니다.</target>       </trans-unit>
        <trans-unit id="113" translate="yes" xml:space="preserve" uid="M:System.ServiceModel.Channels.AddressHeader.CreateAddressHeader(System.Object,System.Runtime.Serialization.XmlObjectSerializer)">
          <source>The information item for the address header.</source>
          <target state="translated">주소 헤더의 정보 항목입니다.</target>       </trans-unit>
        <trans-unit id="114" translate="yes" xml:space="preserve" uid="M:System.ServiceModel.Channels.AddressHeader.CreateAddressHeader(System.Object,System.Runtime.Serialization.XmlObjectSerializer)">
          <source>The <ph id="ph1">&lt;see cref="T:System.Runtime.Serialization.XmlObjectSerializer" /&gt;</ph> used to serialize the specified object in the <bpt id="p1">&lt;c&gt;</bpt>value<ept id="p1">&lt;/c&gt;</ept> parameter.</source>
          <target state="translated"><bpt id="p1">&lt;c&gt;</bpt>value<ept id="p1">&lt;/c&gt;</ept> 매개 변수에서 지정된 개체를 serialize하는 데 사용되는 <ph id="ph1">&lt;see cref="T:System.Runtime.Serialization.XmlObjectSerializer" /&gt;</ph>입니다.</target>       </trans-unit>
        <trans-unit id="115" translate="yes" xml:space="preserve" uid="M:System.ServiceModel.Channels.AddressHeader.CreateAddressHeader(System.Object,System.Runtime.Serialization.XmlObjectSerializer)">
          <source>Creates a new instance of the <ph id="ph1">&lt;see cref="T:System.ServiceModel.Channels.AddressHeader" /&gt;</ph> class using a specified formatter to serialize the information item from a specified object.</source>
          <target state="translated">지정된 포맷터를 사용하여 지정된 개체에서 정보 항목을 serialize하여 <ph id="ph1">&lt;see cref="T:System.ServiceModel.Channels.AddressHeader" /&gt;</ph> 클래스의 새 인스턴스를 만듭니다.</target>       </trans-unit>
        <trans-unit id="116" translate="yes" xml:space="preserve" uid="M:System.ServiceModel.Channels.AddressHeader.CreateAddressHeader(System.Object,System.Runtime.Serialization.XmlObjectSerializer)">
          <source>The <ph id="ph1">&lt;see cref="T:System.ServiceModel.Channels.AddressHeader" /&gt;</ph> that contains the information item specified by the value parameter.</source>
          <target state="translated">값 매개 변수에 의해 지정된 정보 항목을 포함하는 <ph id="ph1">&lt;see cref="T:System.ServiceModel.Channels.AddressHeader" /&gt;</ph>입니다.</target>       </trans-unit>
        <trans-unit id="117" translate="yes" xml:space="preserve" extradata="MT" uid="M:System.ServiceModel.Channels.AddressHeader.CreateAddressHeader(System.Object,System.Runtime.Serialization.XmlObjectSerializer)">
          <source>The following example shows how to create an address header using this method.</source>
          <target state="translated">@FSHO1@다음 예제에서는 이 메서드를 사용하여 주소 헤더를 만드는 방법을 보여 줍니다.</target>       </trans-unit>
        <trans-unit id="118" translate="yes" xml:space="preserve" uid="M:System.ServiceModel.Channels.AddressHeader.CreateAddressHeader(System.Object,System.Runtime.Serialization.XmlObjectSerializer)">
          <source>The <ph id="ph1">&lt;paramref name="formatter" /&gt;</ph> is <ph id="ph2">&lt;see langword="null" /&gt;</ph>.</source>
          <target state="translated"><ph id="ph1">&lt;paramref name="formatter" /&gt;</ph>이 <ph id="ph2">&lt;see langword="null" /&gt;</ph>인 경우</target>       </trans-unit>
        <trans-unit id="119" translate="yes" xml:space="preserve" uid="M:System.ServiceModel.Channels.AddressHeader.CreateAddressHeader(System.String,System.String,System.Object)">
          <source>The name of the address header.</source>
          <target state="translated">주소 헤더의 이름입니다.</target>       </trans-unit>
        <trans-unit id="120" translate="yes" xml:space="preserve" uid="M:System.ServiceModel.Channels.AddressHeader.CreateAddressHeader(System.String,System.String,System.Object)">
          <source>The namespace of the address header.</source>
          <target state="translated">주소 헤더의 네임스페이스입니다.</target>       </trans-unit>
        <trans-unit id="121" translate="yes" xml:space="preserve" uid="M:System.ServiceModel.Channels.AddressHeader.CreateAddressHeader(System.String,System.String,System.Object)">
          <source>The information item for the address header.</source>
          <target state="translated">주소 헤더의 정보 항목입니다.</target>       </trans-unit>
        <trans-unit id="122" translate="yes" xml:space="preserve" uid="M:System.ServiceModel.Channels.AddressHeader.CreateAddressHeader(System.String,System.String,System.Object)">
          <source>Creates a new instance of the <ph id="ph1">&lt;see cref="T:System.ServiceModel.Channels.AddressHeader" /&gt;</ph> class with a specified value, name and namespace.</source>
          <target state="translated">지정된 값, 이름 및 네임스페이스를 사용하여 <ph id="ph1">&lt;see cref="T:System.ServiceModel.Channels.AddressHeader" /&gt;</ph> 클래스의 새 인스턴스를 만듭니다.</target>       </trans-unit>
        <trans-unit id="123" translate="yes" xml:space="preserve" uid="M:System.ServiceModel.Channels.AddressHeader.CreateAddressHeader(System.String,System.String,System.Object)">
          <source>The <ph id="ph1">&lt;see cref="T:System.ServiceModel.Channels.AddressHeader" /&gt;</ph> with the specified <ph id="ph2">&lt;paramref name="name" /&gt;</ph> and <ph id="ph3">&lt;paramref name="ns" /&gt;</ph> that contains the information item specified by <ph id="ph4">&lt;paramref name="value" /&gt;</ph>.</source>
          <target state="translated">지정된 <ph id="ph1">&lt;see cref="T:System.ServiceModel.Channels.AddressHeader" /&gt;</ph> 및 <ph id="ph2">&lt;paramref name="name" /&gt;</ph>가 있는 <ph id="ph3">&lt;paramref name="ns" /&gt;</ph>이며, <ph id="ph4">&lt;paramref name="value" /&gt;</ph>로 지정된 정보 항목을 포함합니다.</target>       </trans-unit>
        <trans-unit id="124" translate="yes" xml:space="preserve" extradata="MT" uid="M:System.ServiceModel.Channels.AddressHeader.CreateAddressHeader(System.String,System.String,System.Object)">
          <source>The following example shows how to create an address header using this method.</source>
          <target state="translated">@FSHO1@다음 예제에서는 이 메서드를 사용하여 주소 헤더를 만드는 방법을 보여 줍니다.</target>       </trans-unit>
        <trans-unit id="125" translate="yes" xml:space="preserve" uid="M:System.ServiceModel.Channels.AddressHeader.CreateAddressHeader(System.String,System.String,System.Object)">
          <source>The <ph id="ph1">&lt;paramref name="name" /&gt;</ph> is <ph id="ph2">&lt;see langword="null" /&gt;</ph> or <ph id="ph3">&lt;paramref name="name" /&gt;</ph>.Length == 0.</source>
          <target state="translated"><ph id="ph1">&lt;paramref name="name" /&gt;</ph>이 <ph id="ph2">&lt;see langword="null" /&gt;</ph> 또는 <ph id="ph3">&lt;paramref name="name" /&gt;</ph>.Length == 0인 경우</target>       </trans-unit>
        <trans-unit id="126" translate="yes" xml:space="preserve" uid="M:System.ServiceModel.Channels.AddressHeader.CreateAddressHeader(System.String,System.String,System.Object,System.Runtime.Serialization.XmlObjectSerializer)">
          <source>The name of the address header.</source>
          <target state="translated">주소 헤더의 이름입니다.</target>       </trans-unit>
        <trans-unit id="127" translate="yes" xml:space="preserve" uid="M:System.ServiceModel.Channels.AddressHeader.CreateAddressHeader(System.String,System.String,System.Object,System.Runtime.Serialization.XmlObjectSerializer)">
          <source>The namespace of the address header.</source>
          <target state="translated">주소 헤더의 네임스페이스입니다.</target>       </trans-unit>
        <trans-unit id="128" translate="yes" xml:space="preserve" uid="M:System.ServiceModel.Channels.AddressHeader.CreateAddressHeader(System.String,System.String,System.Object,System.Runtime.Serialization.XmlObjectSerializer)">
          <source>The information item for the address header.</source>
          <target state="translated">주소 헤더의 정보 항목입니다.</target>       </trans-unit>
        <trans-unit id="129" translate="yes" xml:space="preserve" uid="M:System.ServiceModel.Channels.AddressHeader.CreateAddressHeader(System.String,System.String,System.Object,System.Runtime.Serialization.XmlObjectSerializer)">
          <source>The <ph id="ph1">&lt;see cref="T:System.Runtime.Serialization.XmlObjectSerializer" /&gt;</ph> used to serialize the specified object in the <bpt id="p1">&lt;c&gt;</bpt>value<ept id="p1">&lt;/c&gt;</ept> parameter.</source>
          <target state="translated"><bpt id="p1">&lt;c&gt;</bpt>value<ept id="p1">&lt;/c&gt;</ept> 매개 변수에서 지정된 개체를 serialize하는 데 사용되는 <ph id="ph1">&lt;see cref="T:System.Runtime.Serialization.XmlObjectSerializer" /&gt;</ph>입니다.</target>       </trans-unit>
        <trans-unit id="130" translate="yes" xml:space="preserve" uid="M:System.ServiceModel.Channels.AddressHeader.CreateAddressHeader(System.String,System.String,System.Object,System.Runtime.Serialization.XmlObjectSerializer)">
          <source>Creates a new instance of the <ph id="ph1">&lt;see cref="T:System.ServiceModel.Channels.AddressHeader" /&gt;</ph> class with a specified name and namespace that uses a specified formatter to serialize the information item from a specified object.</source>
          <target state="translated">지정된 포맷터를 사용하여 지정된 개체에서 정보 항목을 serialize하고 지정된 이름과 네임스페이스를 사용하여 <ph id="ph1">&lt;see cref="T:System.ServiceModel.Channels.AddressHeader" /&gt;</ph> 클래스의 새 인스턴스를 만듭니다.</target>       </trans-unit>
        <trans-unit id="131" translate="yes" xml:space="preserve" uid="M:System.ServiceModel.Channels.AddressHeader.CreateAddressHeader(System.String,System.String,System.Object,System.Runtime.Serialization.XmlObjectSerializer)">
          <source>The <ph id="ph1">&lt;see cref="T:System.ServiceModel.Channels.AddressHeader" /&gt;</ph> with the specified <ph id="ph2">&lt;paramref name="name" /&gt;</ph> and <ph id="ph3">&lt;paramref name="ns" /&gt;</ph> that contains the information item specified by <ph id="ph4">&lt;paramref name="value" /&gt;</ph>.</source>
          <target state="translated">지정된 <ph id="ph1">&lt;see cref="T:System.ServiceModel.Channels.AddressHeader" /&gt;</ph> 및 <ph id="ph2">&lt;paramref name="name" /&gt;</ph>가 있는 <ph id="ph3">&lt;paramref name="ns" /&gt;</ph>이며, <ph id="ph4">&lt;paramref name="value" /&gt;</ph>로 지정된 정보 항목을 포함합니다.</target>       </trans-unit>
        <trans-unit id="132" translate="yes" xml:space="preserve" extradata="MT" uid="M:System.ServiceModel.Channels.AddressHeader.CreateAddressHeader(System.String,System.String,System.Object,System.Runtime.Serialization.XmlObjectSerializer)">
          <source>The following example shows how to create an address header using this method.</source>
          <target state="translated">@FSHO1@다음 예제에서는 이 메서드를 사용하여 주소 헤더를 만드는 방법을 보여 줍니다.</target>       </trans-unit>
        <trans-unit id="133" translate="yes" xml:space="preserve" uid="M:System.ServiceModel.Channels.AddressHeader.CreateAddressHeader(System.String,System.String,System.Object,System.Runtime.Serialization.XmlObjectSerializer)">
          <source><ph id="ph1">&lt;paramref name="name" /&gt;</ph> or <ph id="ph2">&lt;paramref name="serializer" /&gt;</ph> is <ph id="ph3">&lt;see langword="null" /&gt;</ph> or <ph id="ph4">&lt;paramref name="name" /&gt;</ph>.Length == 0.</source>
          <target state="translated"><ph id="ph1">&lt;paramref name="name" /&gt;</ph> 또는 <ph id="ph2">&lt;paramref name="serializer" /&gt;</ph>가 <ph id="ph3">&lt;see langword="null" /&gt;</ph> 또는 <ph id="ph4">&lt;paramref name="name" /&gt;</ph>.Length == 0인 경우</target>       </trans-unit>
        <trans-unit id="134" translate="yes" xml:space="preserve" uid="M:System.ServiceModel.Channels.AddressHeader.Equals(System.Object)">
          <source>The <ph id="ph1">&lt;see cref="T:System.Object" /&gt;</ph> to compare with the object contained in the current address header.</source>
          <target state="translated">현재 주소 헤더에 포함된 개체와 비교할 <ph id="ph1">&lt;see cref="T:System.Object" /&gt;</ph>입니다.</target>       </trans-unit>
        <trans-unit id="135" translate="yes" xml:space="preserve" uid="M:System.ServiceModel.Channels.AddressHeader.Equals(System.Object)">
          <source>Determines whether the information item in a specified object is equal to the object contained in the current address header.</source>
          <target state="translated">지정된 개체의 정보 항목이 현재 주소 헤더에 포함된 개체와 같은지 여부를 결정합니다.</target>       </trans-unit>
        <trans-unit id="136" translate="yes" xml:space="preserve" uid="M:System.ServiceModel.Channels.AddressHeader.Equals(System.Object)">
          <source><ph id="ph1">&lt;see langword="true" /&gt;</ph> if the information item in a specified <ph id="ph2">&lt;paramref name="obj" /&gt;</ph> is equivalent to the information item contained in the current address header; otherwise, <ph id="ph3">&lt;see langword="false" /&gt;</ph>.</source>
          <target state="translated">지정된 <ph id="ph1">&lt;see langword="true" /&gt;</ph>의 정보 항목이 현재 주소 헤더에 포함된 정보 항목과 같으면 <ph id="ph2">&lt;paramref name="obj" /&gt;</ph>이고, 그렇지 않으면 <ph id="ph3">&lt;see langword="false" /&gt;</ph>입니다.</target>       </trans-unit>
        <trans-unit id="137" translate="yes" xml:space="preserve" uid="M:System.ServiceModel.Channels.AddressHeader.Equals(System.Object)">
          <source>In particular, returns <ph id="ph1">&lt;see langword="false" /&gt;</ph> if <ph id="ph2">&lt;paramref name="obj" /&gt;</ph> is <ph id="ph3">&lt;see langword="null" /&gt;</ph>.</source>
          <target state="translated">특히, <ph id="ph1">&lt;see langword="false" /&gt;</ph>가 <ph id="ph2">&lt;paramref name="obj" /&gt;</ph>이면 <ph id="ph3">&lt;see langword="null" /&gt;</ph>를 반환합니다.</target>       </trans-unit>
        <trans-unit id="138" translate="yes" xml:space="preserve" extradata="MT" uid="M:System.ServiceModel.Channels.AddressHeader.Equals(System.Object)">
          <source>Checks for equivalence of serialized canonical XML between the information items.</source>
          <target state="translated">두 정보 항목 간에 serialize된 정식 XML이 같은지 확인합니다.</target>       </trans-unit>
        <trans-unit id="139" translate="yes" xml:space="preserve" extradata="MT" uid="M:System.ServiceModel.Channels.AddressHeader.Equals(System.Object)">
          <source>The following example shows how to call this method.</source>
          <target state="translated">@FSHO1@다음 예제에서는 이 메서드를 호출하는 방법을 보여 줍니다.</target>       </trans-unit>
        <trans-unit id="140" translate="yes" xml:space="preserve" uid="M:System.ServiceModel.Channels.AddressHeader.GetAddressHeaderReader">
          <source>Returns an XML reader that can serialize the current address header object.</source>
          <target state="translated">현재 주소 헤더 개체를 serialize할 수 있는 XML 판독기를 반환합니다.</target>       </trans-unit>
        <trans-unit id="141" translate="yes" xml:space="preserve" uid="M:System.ServiceModel.Channels.AddressHeader.GetAddressHeaderReader">
          <source>An instance of <ph id="ph1">&lt;see cref="T:System.Xml.XmlDictionaryReader" /&gt;</ph> that can serialize the current address header object.</source>
          <target state="translated">현재 주소 헤더 개체를 serialize할 수 있는 <ph id="ph1">&lt;see cref="T:System.Xml.XmlDictionaryReader" /&gt;</ph>의 인스턴스입니다.</target>       </trans-unit>
        <trans-unit id="142" translate="yes" xml:space="preserve" extradata="MT" uid="M:System.ServiceModel.Channels.AddressHeader.GetAddressHeaderReader">
          <source>The following example shows how to call this method.</source>
          <target state="translated">@FSHO1@다음 예제에서는 이 메서드를 호출하는 방법을 보여 줍니다.</target>       </trans-unit>
        <trans-unit id="143" translate="yes" xml:space="preserve" uid="M:System.ServiceModel.Channels.AddressHeader.GetHashCode">
          <source>Provides a unique hash code for an address header.</source>
          <target state="translated">주소 헤더에 대한 고유 해시 코드를 제공합니다.</target>       </trans-unit>
        <trans-unit id="144" translate="yes" xml:space="preserve" uid="M:System.ServiceModel.Channels.AddressHeader.GetHashCode">
          <source>A unique hash code for the current address header.</source>
          <target state="translated">현재 주소 헤더에 대한 고유 해시 코드입니다.</target>       </trans-unit>
        <trans-unit id="145" translate="yes" xml:space="preserve" extradata="MT" uid="M:System.ServiceModel.Channels.AddressHeader.GetHashCode">
          <source>This is the string-based implementation.</source>
          <target state="translated">문자열 기반 구현입니다.</target>       </trans-unit>
        <trans-unit id="146" translate="yes" xml:space="preserve" extradata="MT" uid="M:System.ServiceModel.Channels.AddressHeader.GetHashCode">
          <source><ph id="ph1">&lt;xref:System.ServiceModel.Channels.AddressHeader.GetHashCode%2A&gt;</ph> is suitable for use in hashing algorithms and data structures like a hash table.</source>
          <target state="translated"><ph id="ph1">&lt;xref:System.ServiceModel.Channels.AddressHeader.GetHashCode%2A&gt;</ph>는 해시 알고리즘 및 해시 테이블과 같은 데이터 구조에서 사용하기에 적합합니다.</target>       </trans-unit>
        <trans-unit id="147" translate="yes" xml:space="preserve" extradata="MT" uid="M:System.ServiceModel.Channels.AddressHeader.GetHashCode">
          <source>The following example shows how to call this method.</source>
          <target state="translated">@FSHO1@다음 예제에서는 이 메서드를 호출하는 방법을 보여 줍니다.</target>       </trans-unit>
        <trans-unit id="148" translate="yes" xml:space="preserve" uid="T:System.ServiceModel.Channels.AddressHeader">
          <source>Deserializes the information item from the current address header object.</source>
          <target state="translated">현재 주소 헤더 개체에서 정보 항목을 deserialize합니다.</target>       </trans-unit>
        <trans-unit id="149" translate="yes" xml:space="preserve" extradata="MT" uid="T:System.ServiceModel.Channels.AddressHeader">
          <source>Use the <ph id="ph1">&lt;xref:System.ServiceModel.Channels.AddressHeader.GetValue%60%601%28System.Runtime.Serialization.XmlObjectSerializer%29&gt;</ph> overload if you want to use a customized XML formatter; otherwise use the <ph id="ph2">&lt;xref:System.ServiceModel.Channels.AddressHeader.GetValue%60%601&gt;</ph> overload.</source>
          <target state="translated">사용자 지정 XML 포맷터를 사용하려면 <ph id="ph1">&lt;xref:System.ServiceModel.Channels.AddressHeader.GetValue%60%601%28System.Runtime.Serialization.XmlObjectSerializer%29&gt;</ph> 오버로드를 사용하고, 그렇지 않으면 <ph id="ph2">&lt;xref:System.ServiceModel.Channels.AddressHeader.GetValue%60%601&gt;</ph> 오버로드를 사용합니다.</target>       </trans-unit>
        <trans-unit id="150" translate="yes" xml:space="preserve" extradata="MT" uid="M:System.ServiceModel.Channels.AddressHeader.GetValue``1">
          <source>A class of type <bpt id="p1">&lt;c&gt;</bpt>T<ept id="p1">&lt;/c&gt;</ept> with its fields and properties set to the values supplied by the current address header object.</source>
          <target state="translated">형식의 클래스 <bpt id="p1">&lt;c&gt;</bpt>T<ept id="p1">&lt;/c&gt;</ept> 변수 필드와 속성이 현재 주소 헤더 개체에 의해 제공 된 값으로 설정 합니다.</target>       </trans-unit>
        <trans-unit id="151" translate="yes" xml:space="preserve" uid="M:System.ServiceModel.Channels.AddressHeader.GetValue``1">
          <source>Deserializes the information item from the current address header to an object of a specified type.</source>
          <target state="translated">현재 주소 헤더의 정보 항목을 지정된 형식의 개체로 deserialize합니다.</target>       </trans-unit>
        <trans-unit id="152" translate="yes" xml:space="preserve" uid="M:System.ServiceModel.Channels.AddressHeader.GetValue``1">
          <source>An instance of a class of type <ph id="ph1">&lt;paramref name="T" /&gt;</ph> with its fields and properties set to the values supplied by the current address header object.</source>
          <target state="translated">현재 주소 헤더 개체에 의해 제공된 값으로 설정된 필드와 속성이 있는 <ph id="ph1">&lt;paramref name="T" /&gt;</ph>  형식 클래스의 인스턴스입니다.</target>       </trans-unit>
        <trans-unit id="153" translate="yes" xml:space="preserve" extradata="MT" uid="M:System.ServiceModel.Channels.AddressHeader.GetValue``1">
          <source>When using this overload, you must supply a type for the generic parameter <ph id="ph1">`T`</ph>.</source>
          <target state="translated">이 오버로드를 사용할 때는 제네릭 매개 변수 <ph id="ph1">`T`</ph>의 형식을 제공해야 합니다.</target>       </trans-unit>
        <trans-unit id="154" translate="yes" xml:space="preserve" extradata="MT" uid="M:System.ServiceModel.Channels.AddressHeader.GetValue``1">
          <source>The type of the return value is determined by the generic type parameter.</source>
          <target state="translated">반환 값의 형식은 제네릭 형식 매개 변수에 의해 결정됩니다.</target>       </trans-unit>
        <trans-unit id="155" translate="yes" xml:space="preserve" extradata="MT" uid="M:System.ServiceModel.Channels.AddressHeader.GetValue``1">
          <source>Use the <ph id="ph1">&lt;xref:System.ServiceModel.Channels.AddressHeader.GetValue%60%601%28System.Runtime.Serialization.XmlObjectSerializer%29&gt;</ph> overload if you want to use a customized XML formatter.</source>
          <target state="translated">사용자 지정 XML 포맷터를 사용하려면 <ph id="ph1">&lt;xref:System.ServiceModel.Channels.AddressHeader.GetValue%60%601%28System.Runtime.Serialization.XmlObjectSerializer%29&gt;</ph> 오버로드를 사용합니다.</target>       </trans-unit>
        <trans-unit id="156" translate="yes" xml:space="preserve" extradata="MT" uid="M:System.ServiceModel.Channels.AddressHeader.GetValue``1">
          <source>The following example shows how to call this method.</source>
          <target state="translated">@FSHO1@다음 예제에서는 이 메서드를 호출하는 방법을 보여 줍니다.</target>       </trans-unit>
        <trans-unit id="157" translate="yes" xml:space="preserve" extradata="MT" uid="M:System.ServiceModel.Channels.AddressHeader.GetValue``1(System.Runtime.Serialization.XmlObjectSerializer)">
          <source>A class of type <bpt id="p1">&lt;c&gt;</bpt>T<ept id="p1">&lt;/c&gt;</ept> with its fields and properties set to the values supplied by the current address header object.</source>
          <target state="translated">형식의 클래스 <bpt id="p1">&lt;c&gt;</bpt>T<ept id="p1">&lt;/c&gt;</ept> 변수 필드와 속성이 현재 주소 헤더 개체에 의해 제공 된 값으로 설정 합니다.</target>       </trans-unit>
        <trans-unit id="158" translate="yes" xml:space="preserve" uid="M:System.ServiceModel.Channels.AddressHeader.GetValue``1(System.Runtime.Serialization.XmlObjectSerializer)">
          <source>The <ph id="ph1">&lt;see cref="T:System.Runtime.Serialization.XmlObjectSerializer" /&gt;</ph> used to deserialize the information item from the current address header object.</source>
          <target state="translated">현재 주소 헤더 개체의 정보 항목을 deserialize하는 데 사용되는 <ph id="ph1">&lt;see cref="T:System.Runtime.Serialization.XmlObjectSerializer" /&gt;</ph>입니다.</target>       </trans-unit>
        <trans-unit id="159" translate="yes" xml:space="preserve" uid="M:System.ServiceModel.Channels.AddressHeader.GetValue``1(System.Runtime.Serialization.XmlObjectSerializer)">
          <source>Deserializes the information item from the current address header to an object of a specified type that uses a specified formatter to serialize this information.</source>
          <target state="translated">현재 주소 헤더의 정보 항목을 지정된 포맷터를 사용하여 이 정보를 serialize하는 지정된 형식의 개체로 deserialize합니다.</target>       </trans-unit>
        <trans-unit id="160" translate="yes" xml:space="preserve" uid="M:System.ServiceModel.Channels.AddressHeader.GetValue``1(System.Runtime.Serialization.XmlObjectSerializer)">
          <source>An instance of a class of type <ph id="ph1">&lt;paramref name="T" /&gt;</ph> with its fields and properties set to the values supplied by the current address header object.</source>
          <target state="translated">현재 주소 헤더 개체에 의해 제공된 값으로 설정된 필드와 속성이 있는 <ph id="ph1">&lt;paramref name="T" /&gt;</ph>  형식 클래스의 인스턴스입니다.</target>       </trans-unit>
        <trans-unit id="161" translate="yes" xml:space="preserve" extradata="MT" uid="M:System.ServiceModel.Channels.AddressHeader.GetValue``1(System.Runtime.Serialization.XmlObjectSerializer)">
          <source>When using this overload, you must supply a type for the generic parameter <ph id="ph1">`T`</ph>.</source>
          <target state="translated">이 오버로드를 사용할 때는 제네릭 매개 변수 <ph id="ph1">`T`</ph>의 형식을 제공해야 합니다.</target>       </trans-unit>
        <trans-unit id="162" translate="yes" xml:space="preserve" extradata="MT" uid="M:System.ServiceModel.Channels.AddressHeader.GetValue``1(System.Runtime.Serialization.XmlObjectSerializer)">
          <source>The type of the return value is determined by the generic type parameter.</source>
          <target state="translated">반환 값의 형식은 제네릭 형식 매개 변수에 의해 결정됩니다.</target>       </trans-unit>
        <trans-unit id="163" translate="yes" xml:space="preserve" extradata="MT" uid="M:System.ServiceModel.Channels.AddressHeader.GetValue``1(System.Runtime.Serialization.XmlObjectSerializer)">
          <source>Use this overload only if you want to use a customized XML formatter; otherwise use the <ph id="ph1">&lt;xref:System.ServiceModel.Channels.AddressHeader.GetValue%60%601&gt;</ph> overload.</source>
          <target state="translated">사용자 지정 XML 포맷터를 사용하려는 경우에만 이 오버로드를 사용하고, 그렇지 않으면 <ph id="ph1">&lt;xref:System.ServiceModel.Channels.AddressHeader.GetValue%60%601&gt;</ph> 오버로드를 사용합니다.</target>       </trans-unit>
        <trans-unit id="164" translate="yes" xml:space="preserve" extradata="MT" uid="M:System.ServiceModel.Channels.AddressHeader.GetValue``1(System.Runtime.Serialization.XmlObjectSerializer)">
          <source>The following example shows how to call this method.</source>
          <target state="translated">@FSHO1@다음 예제에서는 이 메서드를 호출하는 방법을 보여 줍니다.</target>       </trans-unit>
        <trans-unit id="165" translate="yes" xml:space="preserve" uid="M:System.ServiceModel.Channels.AddressHeader.GetValue``1(System.Runtime.Serialization.XmlObjectSerializer)">
          <source>The <ph id="ph1">&lt;paramref name="serializer" /&gt;</ph> is <ph id="ph2">&lt;see langword="null" /&gt;</ph>.</source>
          <target state="translated"><ph id="ph1">&lt;paramref name="serializer" /&gt;</ph>이 <ph id="ph2">&lt;see langword="null" /&gt;</ph>인 경우</target>       </trans-unit>
        <trans-unit id="166" translate="yes" xml:space="preserve" uid="P:System.ServiceModel.Channels.AddressHeader.Name">
          <source>When implemented, gets the name of the address header.</source>
          <target state="translated">구현되는 경우 주소 헤더의 이름을 가져옵니다.</target>       </trans-unit>
        <trans-unit id="167" translate="yes" xml:space="preserve" extradata="MT" uid="P:System.ServiceModel.Channels.AddressHeader.Name">
          <source>The name of the address header.</source>
          <target state="translated">주소 헤더의 이름입니다.</target>       </trans-unit>
        <trans-unit id="168" translate="yes" xml:space="preserve" extradata="MT" uid="P:System.ServiceModel.Channels.AddressHeader.Name">
          <source>The following example shows how to access this property.</source>
          <target state="translated">다음 예제에서는 이 속성에 액세스하는 방법을 보여 줍니다.</target>       </trans-unit>
        <trans-unit id="169" translate="yes" xml:space="preserve" uid="P:System.ServiceModel.Channels.AddressHeader.Namespace">
          <source>When implemented, gets the namespace of the address header.</source>
          <target state="translated">구현되는 경우 주소 헤더의 네임스페이스를 가져옵니다.</target>       </trans-unit>
        <trans-unit id="170" translate="yes" xml:space="preserve" extradata="MT" uid="P:System.ServiceModel.Channels.AddressHeader.Namespace">
          <source>The namespace of the address header.</source>
          <target state="translated">주소 헤더의 네임스페이스입니다.</target>       </trans-unit>
        <trans-unit id="171" translate="yes" xml:space="preserve" extradata="MT" uid="P:System.ServiceModel.Channels.AddressHeader.Namespace">
          <source>The following example shows how to access this property.</source>
          <target state="translated">다음 예제에서는 이 속성에 액세스하는 방법을 보여 줍니다.</target>       </trans-unit>
        <trans-unit id="172" translate="yes" xml:space="preserve" uid="M:System.ServiceModel.Channels.AddressHeader.OnWriteAddressHeaderContents(System.Xml.XmlDictionaryWriter)">
          <source>The <ph id="ph1">&lt;see cref="T:System.Xml.XmlDictionaryWriter" /&gt;</ph> used to write the address header contents to a stream or file.</source>
          <target state="translated">주소 헤더 콘텐츠를 스트림 또는 파일에 쓰는 데 사용되는 <ph id="ph1">&lt;see cref="T:System.Xml.XmlDictionaryWriter" /&gt;</ph>입니다.</target>       </trans-unit>
        <trans-unit id="173" translate="yes" xml:space="preserve" uid="M:System.ServiceModel.Channels.AddressHeader.OnWriteAddressHeaderContents(System.Xml.XmlDictionaryWriter)">
          <source>When overridden in a derived class, is invoked when the address header contents are written to a stream or file.</source>
          <target state="translated">파생 클래스에서 재정의되는 경우 주소 헤더 콘텐츠를 스트림 또는 파일에 쓸 때 호출됩니다.</target>       </trans-unit>
        <trans-unit id="174" translate="yes" xml:space="preserve" uid="M:System.ServiceModel.Channels.AddressHeader.OnWriteStartAddressHeader(System.Xml.XmlDictionaryWriter)">
          <source>The <ph id="ph1">&lt;see cref="T:System.Xml.XmlDictionaryWriter" /&gt;</ph> used to write the address header to a stream or file.</source>
          <target state="translated">주소 헤더를 스트림 또는 파일에 쓰는 데 사용되는 <ph id="ph1">&lt;see cref="T:System.Xml.XmlDictionaryWriter" /&gt;</ph>입니다.</target>       </trans-unit>
        <trans-unit id="175" translate="yes" xml:space="preserve" uid="M:System.ServiceModel.Channels.AddressHeader.OnWriteStartAddressHeader(System.Xml.XmlDictionaryWriter)">
          <source>When overridden in a derived class, is invoked when the address header contents begin to be written to a stream or file.</source>
          <target state="translated">파생 클래스에서 재정의되는 경우 주소 헤더 콘텐츠를 스트림 또는 파일에 쓰기 시작할 때 호출됩니다.</target>       </trans-unit>
        <trans-unit id="176" translate="yes" xml:space="preserve" uid="M:System.ServiceModel.Channels.AddressHeader.ToMessageHeader">
          <source>Wraps the address header as a message header.</source>
          <target state="translated">주소 헤더를 메시지 헤더로 래핑합니다.</target>       </trans-unit>
        <trans-unit id="177" translate="yes" xml:space="preserve" uid="M:System.ServiceModel.Channels.AddressHeader.ToMessageHeader">
          <source>The <ph id="ph1">&lt;see cref="T:System.ServiceModel.Channels.MessageHeader" /&gt;</ph> that wraps the current address header.</source>
          <target state="translated">현재 주소 헤더를 래핑하는 <ph id="ph1">&lt;see cref="T:System.ServiceModel.Channels.MessageHeader" /&gt;</ph>입니다.</target>       </trans-unit>
        <trans-unit id="178" translate="yes" xml:space="preserve" extradata="MT" uid="M:System.ServiceModel.Channels.AddressHeader.ToMessageHeader">
          <source>The following example shows how to call this method.</source>
          <target state="translated">@FSHO1@다음 예제에서는 이 메서드를 호출하는 방법을 보여 줍니다.</target>       </trans-unit>
        <trans-unit id="179" translate="yes" xml:space="preserve" uid="T:System.ServiceModel.Channels.AddressHeader">
          <source>Writes the address header to a stream or file.</source>
          <target state="translated">주소 헤더를 스트림 또는 파일에 씁니다.</target>       </trans-unit>
        <trans-unit id="180" translate="yes" xml:space="preserve" extradata="MT" uid="T:System.ServiceModel.Channels.AddressHeader">
          <source>The <ph id="ph1">&lt;xref:System.ServiceModel.Channels.AddressHeader.WriteAddressHeader%2A&gt;</ph> and <ph id="ph2">&lt;xref:System.ServiceModel.Channels.AddressHeader.WriteAddressHeader%28System.Xml.XmlWriter%29&gt;</ph> overloads provide interfaces to use in writing an address header to a stream or file.</source>
          <target state="translated"><ph id="ph1">&lt;xref:System.ServiceModel.Channels.AddressHeader.WriteAddressHeader%2A&gt;</ph> 및 <ph id="ph2">&lt;xref:System.ServiceModel.Channels.AddressHeader.WriteAddressHeader%28System.Xml.XmlWriter%29&gt;</ph> 오버로드는 주소 헤더를 스트림 또는 파일에 쓸 때 사용하는 인터페이스를 제공합니다.</target>       </trans-unit>
        <trans-unit id="181" translate="yes" xml:space="preserve" extradata="MT" uid="T:System.ServiceModel.Channels.AddressHeader">
          <source>Both call the abstract <ph id="ph1">&lt;xref:System.ServiceModel.Channels.AddressHeader.OnWriteAddressHeaderContents%28System.Xml.XmlDictionaryWriter%29&gt;</ph> method, so users must provide an implementation of this method to use these overloads.</source>
          <target state="translated">두 가지 모두 추상 <ph id="ph1">&lt;xref:System.ServiceModel.Channels.AddressHeader.OnWriteAddressHeaderContents%28System.Xml.XmlDictionaryWriter%29&gt;</ph> 메서드를 호출하므로 이러한 오버로드를 사용하려면 사용자는 이 메서드의 구현을 제공해야 합니다.</target>       </trans-unit>
        <trans-unit id="182" translate="yes" xml:space="preserve" uid="M:System.ServiceModel.Channels.AddressHeader.WriteAddressHeader(System.Xml.XmlDictionaryWriter)">
          <source>The <ph id="ph1">&lt;see cref="T:System.Xml.XmlDictionaryWriter" /&gt;</ph> used to write the address header to a stream or file.</source>
          <target state="translated">주소 헤더를 스트림 또는 파일에 쓰는 데 사용되는 <ph id="ph1">&lt;see cref="T:System.Xml.XmlDictionaryWriter" /&gt;</ph>입니다.</target>       </trans-unit>
        <trans-unit id="183" translate="yes" xml:space="preserve" uid="M:System.ServiceModel.Channels.AddressHeader.WriteAddressHeader(System.Xml.XmlDictionaryWriter)">
          <source>Writes the address header to a stream or file using a specified <ph id="ph1">&lt;see cref="T:System.Xml.XmlDictionaryWriter" /&gt;</ph>.</source>
          <target state="translated">지정된 <ph id="ph1">&lt;see cref="T:System.Xml.XmlDictionaryWriter" /&gt;</ph>를 사용하여 주소 헤더를 스트림 또는 파일에 씁니다.</target>       </trans-unit>
        <trans-unit id="184" translate="yes" xml:space="preserve" extradata="MT" uid="M:System.ServiceModel.Channels.AddressHeader.WriteAddressHeader(System.Xml.XmlDictionaryWriter)">
          <source>This overload calls the abstract</source>
          <target state="translated">이 오버로드는 추상</target>       </trans-unit>
        <trans-unit id="185" translate="yes" xml:space="preserve" extradata="MT" uid="M:System.ServiceModel.Channels.AddressHeader.WriteAddressHeader(System.Xml.XmlDictionaryWriter)">
          <source><ph id="ph1">&lt;xref:System.ServiceModel.Channels.AddressHeader.OnWriteAddressHeaderContents%28System.Xml.XmlDictionaryWriter%29&gt;</ph> method, so users must provide an implementation of that method to use this method.</source>
          <target state="translated"><ph id="ph1">&lt;xref:System.ServiceModel.Channels.AddressHeader.OnWriteAddressHeaderContents%28System.Xml.XmlDictionaryWriter%29&gt;</ph> 메서드를 호출하므로 이 메서드를 사용하려면 사용자는 이 메서드의 구현을 제공해야 합니다.</target>       </trans-unit>
        <trans-unit id="186" translate="yes" xml:space="preserve" extradata="MT" uid="M:System.ServiceModel.Channels.AddressHeader.WriteAddressHeader(System.Xml.XmlDictionaryWriter)">
          <source>The following example shows how to call this method.</source>
          <target state="translated">@FSHO1@다음 예제에서는 이 메서드를 호출하는 방법을 보여 줍니다.</target>       </trans-unit>
        <trans-unit id="187" translate="yes" xml:space="preserve" uid="M:System.ServiceModel.Channels.AddressHeader.WriteAddressHeader(System.Xml.XmlDictionaryWriter)">
          <source>The <ph id="ph1">&lt;paramref name="writer" /&gt;</ph> is <ph id="ph2">&lt;see langword="null" /&gt;</ph>.</source>
          <target state="translated"><ph id="ph1">&lt;paramref name="writer" /&gt;</ph>이 <ph id="ph2">&lt;see langword="null" /&gt;</ph>인 경우</target>       </trans-unit>
        <trans-unit id="188" translate="yes" xml:space="preserve" uid="M:System.ServiceModel.Channels.AddressHeader.WriteAddressHeader(System.Xml.XmlWriter)">
          <source>The <ph id="ph1">&lt;see cref="T:System.Xml.XmlWriter" /&gt;</ph> used to write the address header to a stream or file.</source>
          <target state="translated">주소 헤더를 스트림 또는 파일에 쓰는 데 사용되는 <ph id="ph1">&lt;see cref="T:System.Xml.XmlWriter" /&gt;</ph>입니다.</target>       </trans-unit>
        <trans-unit id="189" translate="yes" xml:space="preserve" uid="M:System.ServiceModel.Channels.AddressHeader.WriteAddressHeader(System.Xml.XmlWriter)">
          <source>Writes the address header to a stream or file using a specified <ph id="ph1">&lt;see cref="T:System.Xml.XmlWriter" /&gt;</ph>.</source>
          <target state="translated">지정된 <ph id="ph1">&lt;see cref="T:System.Xml.XmlWriter" /&gt;</ph>를 사용하여 주소 헤더를 스트림 또는 파일에 씁니다.</target>       </trans-unit>
        <trans-unit id="190" translate="yes" xml:space="preserve" extradata="MT" uid="M:System.ServiceModel.Channels.AddressHeader.WriteAddressHeader(System.Xml.XmlWriter)">
          <source>This overload wraps <ph id="ph1">&lt;xref:System.Xml.XmlWriter&gt;</ph> as a <ph id="ph2">&lt;xref:System.Xml.XmlDictionaryWriter&gt;</ph> and then the calls the abstract</source>
          <target state="translated">이 오버로드는 <ph id="ph1">&lt;xref:System.Xml.XmlWriter&gt;</ph>를 <ph id="ph2">&lt;xref:System.Xml.XmlDictionaryWriter&gt;</ph>로 래핑한 후 추상</target>       </trans-unit>
        <trans-unit id="191" translate="yes" xml:space="preserve" extradata="MT" uid="M:System.ServiceModel.Channels.AddressHeader.WriteAddressHeader(System.Xml.XmlWriter)">
          <source><ph id="ph1">&lt;xref:System.ServiceModel.Channels.AddressHeader.OnWriteAddressHeaderContents%28System.Xml.XmlDictionaryWriter%29&gt;</ph> method.</source>
          <target state="translated"><ph id="ph1">&lt;xref:System.ServiceModel.Channels.AddressHeader.OnWriteAddressHeaderContents%28System.Xml.XmlDictionaryWriter%29&gt;</ph> 메서드를 호출하여 생성됩니다.</target>       </trans-unit>
        <trans-unit id="192" translate="yes" xml:space="preserve" extradata="MT" uid="M:System.ServiceModel.Channels.AddressHeader.WriteAddressHeader(System.Xml.XmlWriter)">
          <source>Users must provide an implementation for that abstract method to use this overload.</source>
          <target state="translated">이 오버로드를 사용하려면 사용자는 이 추상 메서드에 대한 구현을 제공해야 합니다.</target>       </trans-unit>
        <trans-unit id="193" translate="yes" xml:space="preserve" extradata="MT" uid="M:System.ServiceModel.Channels.AddressHeader.WriteAddressHeader(System.Xml.XmlWriter)">
          <source>The following example shows how to call this method.</source>
          <target state="translated">@FSHO1@다음 예제에서는 이 메서드를 호출하는 방법을 보여 줍니다.</target>       </trans-unit>
        <trans-unit id="194" translate="yes" xml:space="preserve" uid="M:System.ServiceModel.Channels.AddressHeader.WriteAddressHeader(System.Xml.XmlWriter)">
          <source>The <ph id="ph1">&lt;paramref name="writer" /&gt;</ph> is <ph id="ph2">&lt;see langword="null" /&gt;</ph>.</source>
          <target state="translated"><ph id="ph1">&lt;paramref name="writer" /&gt;</ph>이 <ph id="ph2">&lt;see langword="null" /&gt;</ph>인 경우</target>       </trans-unit>
        <trans-unit id="195" translate="yes" xml:space="preserve" uid="M:System.ServiceModel.Channels.AddressHeader.WriteAddressHeaderContents(System.Xml.XmlDictionaryWriter)">
          <source>The <ph id="ph1">&lt;see cref="T:System.Xml.XmlDictionaryWriter" /&gt;</ph> used to write the address header contents to a stream or file.</source>
          <target state="translated">주소 헤더 콘텐츠를 스트림 또는 파일에 쓰는 데 사용되는 <ph id="ph1">&lt;see cref="T:System.Xml.XmlDictionaryWriter" /&gt;</ph>입니다.</target>       </trans-unit>
        <trans-unit id="196" translate="yes" xml:space="preserve" uid="M:System.ServiceModel.Channels.AddressHeader.WriteAddressHeaderContents(System.Xml.XmlDictionaryWriter)">
          <source>Writes the address header contents to a stream or file.</source>
          <target state="translated">주소 헤더 콘텐츠를 스트림 또는 파일에 씁니다.</target>       </trans-unit>
        <trans-unit id="197" translate="yes" xml:space="preserve" extradata="MT" uid="M:System.ServiceModel.Channels.AddressHeader.WriteAddressHeaderContents(System.Xml.XmlDictionaryWriter)">
          <source>The following example shows how to call this method.</source>
          <target state="translated">@FSHO1@다음 예제에서는 이 메서드를 호출하는 방법을 보여 줍니다.</target>       </trans-unit>
        <trans-unit id="198" translate="yes" xml:space="preserve" uid="M:System.ServiceModel.Channels.AddressHeader.WriteAddressHeaderContents(System.Xml.XmlDictionaryWriter)">
          <source>The <ph id="ph1">&lt;paramref name="writer" /&gt;</ph> is <ph id="ph2">&lt;see langword="null" /&gt;</ph>.</source>
          <target state="translated"><ph id="ph1">&lt;paramref name="writer" /&gt;</ph>이 <ph id="ph2">&lt;see langword="null" /&gt;</ph>인 경우</target>       </trans-unit>
        <trans-unit id="199" translate="yes" xml:space="preserve" uid="M:System.ServiceModel.Channels.AddressHeader.WriteStartAddressHeader(System.Xml.XmlDictionaryWriter)">
          <source>The <ph id="ph1">&lt;see cref="T:System.Xml.XmlDictionaryWriter" /&gt;</ph> used to write the address header to a stream or file.</source>
          <target state="translated">주소 헤더를 스트림 또는 파일에 쓰는 데 사용되는 <ph id="ph1">&lt;see cref="T:System.Xml.XmlDictionaryWriter" /&gt;</ph>입니다.</target>       </trans-unit>
        <trans-unit id="200" translate="yes" xml:space="preserve" uid="M:System.ServiceModel.Channels.AddressHeader.WriteStartAddressHeader(System.Xml.XmlDictionaryWriter)">
          <source>Starts to write the address header contents to a stream or file.</source>
          <target state="translated">주소 헤더 콘텐츠를 스트림 또는 파일에 쓰기 시작합니다.</target>       </trans-unit>
        <trans-unit id="201" translate="yes" xml:space="preserve" extradata="MT" uid="M:System.ServiceModel.Channels.AddressHeader.WriteStartAddressHeader(System.Xml.XmlDictionaryWriter)">
          <source>The following example shows how to call this method.</source>
          <target state="translated">@FSHO1@다음 예제에서는 이 메서드를 호출하는 방법을 보여 줍니다.</target>       </trans-unit>
        <trans-unit id="202" translate="yes" xml:space="preserve" uid="M:System.ServiceModel.Channels.AddressHeader.WriteStartAddressHeader(System.Xml.XmlDictionaryWriter)">
          <source>The <ph id="ph1">&lt;paramref name="writer" /&gt;</ph> is <ph id="ph2">&lt;see langword="null" /&gt;</ph>.</source>
          <target state="translated"><ph id="ph1">&lt;paramref name="writer" /&gt;</ph>이 <ph id="ph2">&lt;see langword="null" /&gt;</ph>인 경우</target>       </trans-unit>
      </group>
    </body>
  </file>
</xliff>