<?xml version="1.0" encoding="utf-8"?>
<xliff xmlns="urn:oasis:names:tc:xliff:document:1.2" xmlns:xsi="http://www.w3.org/2001/XMLSchema-instance" version="1.2" xsi:schemaLocation="urn:oasis:names:tc:xliff:document:1.2 xliff-core-1.2-transitional.xsd">
  <file datatype="xml" original="Baml2006Reader.xml" source-language="en-US" target-language="ko-KR">
    <header>
      <tool tool-id="mdxliff" tool-name="mdxliff" tool-version="1.0-15c36f0" tool-company="Microsoft" />
      <xliffext:skl_file_name xmlns:xliffext="urn:microsoft:content:schema:xliffextensions">02cd5861-7ce2-4a82-b358-31f8435a0ac57279232bc5f9fc9868961187b573f2712fca662c.skl</xliffext:skl_file_name>
      <xliffext:version xmlns:xliffext="urn:microsoft:content:schema:xliffextensions">1.2</xliffext:version>
      <xliffext:ms.openlocfilehash xmlns:xliffext="urn:microsoft:content:schema:xliffextensions">7279232bc5f9fc9868961187b573f2712fca662c</xliffext:ms.openlocfilehash>
      <xliffext:ms.sourcegitcommit xmlns:xliffext="urn:microsoft:content:schema:xliffextensions">d31dc2ede16f6f7bc64e90d9f897ff54c4e3869b</xliffext:ms.sourcegitcommit>
      <xliffext:ms.lasthandoff xmlns:xliffext="urn:microsoft:content:schema:xliffextensions">04/03/2018</xliffext:ms.lasthandoff>
      <xliffext:moniker_ids xmlns:xliffext="urn:microsoft:content:schema:xliffextensions">netframework-4.5.1,netframework-4.5.2,netframework-4.5,netframework-4.6.1,netframework-4.6.2,netframework-4.6,netframework-4.7.1,netframework-4.7</xliffext:moniker_ids>
    </header>
    <body>
      <group id="content" extype="content">
        <trans-unit id="101" translate="yes" xml:space="preserve" uid="T:System.Windows.Baml2006.Baml2006Reader">
          <source>Processes XAML in optimized BAML form and produces a XAML node stream.</source>
          <target state="translated">최적화된 BAML 양식에서 XAML을 처리하고 XAML 노드 스트림을 생성합니다.</target>       </trans-unit>
        <trans-unit id="102" translate="yes" xml:space="preserve" extradata="MT" uid="T:System.Windows.Baml2006.Baml2006Reader">
          <source>BAML form is an optimized form of XAML used by the WPF XAML implementation.</source>
          <target state="translated">BAML 형식은 WPF XAML 구현에서 사용 하는 XAML의 ´ ù입니다.</target>       </trans-unit>
        <trans-unit id="103" translate="yes" xml:space="preserve" extradata="MT" uid="T:System.Windows.Baml2006.Baml2006Reader">
          <source>It is optimized in the sense that it uses internal lookups and tokens for commonly used types or members.</source>
          <target state="translated">사용 하 여 내부 조회와 토큰 자주 사용 되는 형식 또는 멤버에 대 한 의미에서 최적화 됩니다.</target>       </trans-unit>
        <trans-unit id="104" translate="yes" xml:space="preserve" extradata="MT" uid="T:System.Windows.Baml2006.Baml2006Reader">
          <source>The optimization is useful as an implementation detail that addresses packaging size and load time for WPF application scenarios that involve XAML.</source>
          <target state="translated">최적화는 XAML을 포함 하는 WPF 응용 프로그램 시나리오에 대 한 패키지 크기와 로드 시간을 해결 하는 구현 정보로 유용 합니다.</target>       </trans-unit>
        <trans-unit id="105" translate="yes" xml:space="preserve" extradata="MT" uid="T:System.Windows.Baml2006.Baml2006Reader">
          <source>The <ph id="ph1">&lt;xref:System.Windows.Baml2006.Baml2006Reader&gt;</ph> reader class constitutes much of the public API surface that a WPF application developer has for interacting with BAML.</source>
          <target state="translated"><ph id="ph1">&lt;xref:System.Windows.Baml2006.Baml2006Reader&gt;</ph> 판독기 클래스는 WPF 응용 프로그램 개발자가 BAML 상호 작용 하기 위한 공용 API 화면의 상당 부분을 구성 합니다.</target>       </trans-unit>
        <trans-unit id="106" translate="yes" xml:space="preserve" extradata="MT" uid="T:System.Windows.Baml2006.Baml2006Reader">
          <source>The XAML optimized to BAML form may need to be localized.</source>
          <target state="translated">BAML 양식 하도록 최적화 되어 XAML 지역화 해야 합니다.</target>       </trans-unit>
        <trans-unit id="107" translate="yes" xml:space="preserve" extradata="MT" uid="T:System.Windows.Baml2006.Baml2006Reader">
          <source>Localization of XAML and possible tools pathways for doing so is not discussed in this topic.</source>
          <target state="translated">이런 작업에 가능한 도구 경로 및 XAML 지역화가이 항목에서 설명 하지 않습니다.</target>       </trans-unit>
        <trans-unit id="108" translate="yes" xml:space="preserve" extradata="MT" uid="T:System.Windows.Baml2006.Baml2006Reader">
          <source>See <bpt id="p1">[</bpt>Globalization for WPF<ept id="p1">](~/docs/framework/wpf/advanced/globalization-for-wpf.md)</ept>.</source>
          <target state="translated">참조 <bpt id="p1">[</bpt>WPF의 전역화<ept id="p1">](~/docs/framework/wpf/advanced/globalization-for-wpf.md)</ept>합니다.</target>       </trans-unit>
        <trans-unit id="109" translate="yes" xml:space="preserve" extradata="MT" uid="T:System.Windows.Baml2006.Baml2006Reader">
          <source><ph id="ph1">&lt;xref:System.Windows.Baml2006.Baml2006Reader&gt;</ph> uses an internally implemented XAML schema context.</source>
          <target state="translated"><ph id="ph1">&lt;xref:System.Windows.Baml2006.Baml2006Reader&gt;</ph> 내부적으로 구현 된 XAML 스키마 컨텍스트를 사용합니다.</target>       </trans-unit>
        <trans-unit id="110" translate="yes" xml:space="preserve" extradata="MT" uid="T:System.Windows.Baml2006.Baml2006Reader">
          <source>This schema context provides the logic necessary for looking up the types in BAML form, including referencing the optimizations and tokens that are inherent in BAML.</source>
          <target state="translated">BAML 양식에서 형식을 찾는 데 필요한 논리를 제공 하는이 스키마 컨텍스트 최적화 및 BAML에 고유한 토큰 참조를 포함 합니다.</target>       </trans-unit>
        <trans-unit id="111" translate="yes" xml:space="preserve" extradata="MT" uid="T:System.Windows.Baml2006.Baml2006Reader">
          <source>The main scenario for <ph id="ph1">&lt;xref:System.Windows.Baml2006.Baml2006Reader&gt;</ph> is to use it as the <ph id="ph2">&lt;xref:System.Xaml.XamlReader&gt;</ph> implementation that you pass to a call to <ph id="ph3">&lt;xref:System.Windows.Markup.XamlReader.Load%2A?displayProperty=nameWithType&gt;</ph>.</source>
          <target state="translated">에 대 한 주요 시나리오 <ph id="ph1">&lt;xref:System.Windows.Baml2006.Baml2006Reader&gt;</ph> 로 사용 하는 것은 <ph id="ph2">&lt;xref:System.Xaml.XamlReader&gt;</ph> 구현에 대 한 호출에 전달 하 <ph id="ph3">&lt;xref:System.Windows.Markup.XamlReader.Load%2A?displayProperty=nameWithType&gt;</ph>합니다.</target>       </trans-unit>
        <trans-unit id="112" translate="yes" xml:space="preserve" uid="T:System.Windows.Baml2006.Baml2006Reader">
          <source>Initializes a new instance of the <ph id="ph1">&lt;see cref="T:System.Windows.Baml2006.Baml2006Reader" /&gt;</ph> class.</source>
          <target state="translated"><ph id="ph1">&lt;see cref="T:System.Windows.Baml2006.Baml2006Reader" /&gt;</ph> 클래스의 새 인스턴스를 초기화합니다.</target>       </trans-unit>
        <trans-unit id="113" translate="yes" xml:space="preserve" uid="M:System.Windows.Baml2006.Baml2006Reader.#ctor(System.IO.Stream)">
          <source>Input stream of source BAML.</source>
          <target state="translated">소스 BAML의 입력 스트림입니다.</target>       </trans-unit>
        <trans-unit id="114" translate="yes" xml:space="preserve" uid="M:System.Windows.Baml2006.Baml2006Reader.#ctor(System.IO.Stream)">
          <source>Initializes a new instance of the <ph id="ph1">&lt;see cref="T:System.Windows.Baml2006.Baml2006Reader" /&gt;</ph> class based on an input stream.</source>
          <target state="translated">입력 스트림에 따라 <ph id="ph1">&lt;see cref="T:System.Windows.Baml2006.Baml2006Reader" /&gt;</ph> 클래스의 새 인스턴스를 초기화합니다.</target>       </trans-unit>
        <trans-unit id="115" translate="yes" xml:space="preserve" uid="M:System.Windows.Baml2006.Baml2006Reader.#ctor(System.IO.Stream)">
          <source><ph id="ph1">&lt;paramref name="stream" /&gt;</ph> is <ph id="ph2">&lt;see langword="null" /&gt;</ph>.</source>
          <target state="translated"><ph id="ph1">&lt;paramref name="stream" /&gt;</ph>가 <ph id="ph2">&lt;see langword="null" /&gt;</ph>인 경우</target>       </trans-unit>
        <trans-unit id="116" translate="yes" xml:space="preserve" uid="M:System.Windows.Baml2006.Baml2006Reader.#ctor(System.String)">
          <source>String that declares a file path to the file that contains BAML to read.</source>
          <target state="translated">읽을 BAML이 들어 있는 파일에 대한 파일 경로를 선언하는 문자열입니다.</target>       </trans-unit>
        <trans-unit id="117" translate="yes" xml:space="preserve" uid="M:System.Windows.Baml2006.Baml2006Reader.#ctor(System.String)">
          <source>Initializes a new instance of the <ph id="ph1">&lt;see cref="T:System.Windows.Baml2006.Baml2006Reader" /&gt;</ph> class, based on the file name of a local file to read.</source>
          <target state="translated">읽을 로컬 파일의 파일 이름에 따라 <ph id="ph1">&lt;see cref="T:System.Windows.Baml2006.Baml2006Reader" /&gt;</ph> 클래스의 새 인스턴스를 초기화합니다.</target>       </trans-unit>
        <trans-unit id="118" translate="yes" xml:space="preserve" uid="M:System.Windows.Baml2006.Baml2006Reader.#ctor(System.String)">
          <source><ph id="ph1">&lt;paramref name="fileName" /&gt;</ph> is <ph id="ph2">&lt;see langword="null" /&gt;</ph>.</source>
          <target state="translated"><ph id="ph1">&lt;paramref name="fileName" /&gt;</ph>가 <ph id="ph2">&lt;see langword="null" /&gt;</ph>인 경우</target>       </trans-unit>
        <trans-unit id="119" translate="yes" xml:space="preserve" uid="M:System.Windows.Baml2006.Baml2006Reader.#ctor(System.IO.Stream,System.Xaml.XamlReaderSettings)">
          <source>Input stream of source BAML.</source>
          <target state="translated">소스 BAML의 입력 스트림입니다.</target>       </trans-unit>
        <trans-unit id="120" translate="yes" xml:space="preserve" uid="M:System.Windows.Baml2006.Baml2006Reader.#ctor(System.IO.Stream,System.Xaml.XamlReaderSettings)">
          <source>Reader settings.</source>
          <target state="translated">판독기 설정입니다.</target>       </trans-unit>
        <trans-unit id="121" translate="yes" xml:space="preserve" uid="M:System.Windows.Baml2006.Baml2006Reader.#ctor(System.IO.Stream,System.Xaml.XamlReaderSettings)">
          <source>Initializes a new instance of the <ph id="ph1">&lt;see cref="T:System.Windows.Baml2006.Baml2006Reader" /&gt;</ph> class based on an input stream and reader settings.</source>
          <target state="translated">입력 스트림 및 판독기 설정에 따라 <ph id="ph1">&lt;see cref="T:System.Windows.Baml2006.Baml2006Reader" /&gt;</ph> 클래스의 새 인스턴스를 초기화합니다.</target>       </trans-unit>
        <trans-unit id="122" translate="yes" xml:space="preserve" extradata="MT" uid="M:System.Windows.Baml2006.Baml2006Reader.#ctor(System.IO.Stream,System.Xaml.XamlReaderSettings)">
          <source><ph id="ph1">&lt;xref:System.Windows.Baml2006.Baml2006Reader&gt;</ph> uses an internal settings class override.</source>
          <target state="translated"><ph id="ph1">&lt;xref:System.Windows.Baml2006.Baml2006Reader&gt;</ph> 내부 설정 클래스 재정의 사용합니다.</target>       </trans-unit>
        <trans-unit id="123" translate="yes" xml:space="preserve" extradata="MT" uid="M:System.Windows.Baml2006.Baml2006Reader.#ctor(System.IO.Stream,System.Xaml.XamlReaderSettings)">
          <source>However you can pass the information that is permitted by the <ph id="ph1">&lt;xref:System.Xaml.XamlReaderSettings&gt;</ph> base class, and your passed settings are internally upgraded to or merged into the internal settings.</source>
          <target state="translated">그러나 있습니다 수 정보를 전달 하는에서 허용 된 <ph id="ph1">&lt;xref:System.Xaml.XamlReaderSettings&gt;</ph> 기본 클래스 및 전달 된 설정에는 내부적으로 업그레이드 또는 내부 설정에 병합 합니다.</target>       </trans-unit>
        <trans-unit id="124" translate="yes" xml:space="preserve" extradata="MT" uid="M:System.Windows.Baml2006.Baml2006Reader.#ctor(System.IO.Stream,System.Xaml.XamlReaderSettings)">
          <source>Passing <ph id="ph1">`null`</ph> for <ph id="ph2">`xamlReaderSettings`</ph> of this signature throws an exception.</source>
          <target state="translated">전달 <ph id="ph1">`null`</ph> 에 대 한 <ph id="ph2">`xamlReaderSettings`</ph> 이 서명의 예외를 throw 합니다.</target>       </trans-unit>
        <trans-unit id="125" translate="yes" xml:space="preserve" extradata="MT" uid="M:System.Windows.Baml2006.Baml2006Reader.#ctor(System.IO.Stream,System.Xaml.XamlReaderSettings)">
          <source>If you have no special settings to report, use the <ph id="ph1">&lt;xref:System.Windows.Baml2006.Baml2006Reader.%23ctor%28System.IO.Stream%29&gt;</ph> signature.</source>
          <target state="translated">사용 하 여 보고서에 특별 한 설정이 없는 경우는 <ph id="ph1">&lt;xref:System.Windows.Baml2006.Baml2006Reader.%23ctor%28System.IO.Stream%29&gt;</ph> 서명 합니다.</target>       </trans-unit>
        <trans-unit id="126" translate="yes" xml:space="preserve" uid="M:System.Windows.Baml2006.Baml2006Reader.#ctor(System.IO.Stream,System.Xaml.XamlReaderSettings)">
          <source><ph id="ph1">&lt;paramref name="stream" /&gt;</ph> or <ph id="ph2">&lt;paramref name="xamlReaderSettings" /&gt;</ph> is <ph id="ph3">&lt;see langword="null" /&gt;</ph>.</source>
          <target state="translated"><ph id="ph1">&lt;paramref name="stream" /&gt;</ph> 또는 <ph id="ph2">&lt;paramref name="xamlReaderSettings" /&gt;</ph>가 <ph id="ph3">&lt;see langword="null" /&gt;</ph>인 경우</target>       </trans-unit>
        <trans-unit id="127" translate="yes" xml:space="preserve" uid="M:System.Windows.Baml2006.Baml2006Reader.Dispose(System.Boolean)">
          <source><ph id="ph1">&lt;see langword="true" /&gt;</ph> to release the managed resources; otherwise, <ph id="ph2">&lt;see langword="false" /&gt;</ph>.</source>
          <target state="translated">관리되는 리소스를 해제하려면 <ph id="ph1">&lt;see langword="true" /&gt;</ph>이고, 그렇지 않으면 <ph id="ph2">&lt;see langword="false" /&gt;</ph>입니다.</target>       </trans-unit>
        <trans-unit id="128" translate="yes" xml:space="preserve" uid="M:System.Windows.Baml2006.Baml2006Reader.Dispose(System.Boolean)">
          <source>Releases the unmanaged resources used by the <ph id="ph1">&lt;see cref="T:System.Windows.Baml2006.Baml2006Reader" /&gt;</ph> and optionally releases the managed resources.</source>
          <target state="translated"><ph id="ph1">&lt;see cref="T:System.Windows.Baml2006.Baml2006Reader" /&gt;</ph>에서 사용하는 관리되지 않는 리소스를 해제하고, 관리되는 리소스를 선택적으로 해제할 수 있습니다.</target>       </trans-unit>
        <trans-unit id="129" translate="yes" xml:space="preserve" uid="P:System.Windows.Baml2006.Baml2006Reader.IsEof">
          <source>Gets a value that reports whether the reader position is at the end of file.</source>
          <target state="translated">판독기 위치가 파일 끝인지 여부를 보고하는 값을 가져옵니다.</target>       </trans-unit>
        <trans-unit id="130" translate="yes" xml:space="preserve" extradata="MT" uid="P:System.Windows.Baml2006.Baml2006Reader.IsEof">
          <source><ph id="ph1">&lt;see langword="true" /&gt;</ph> if the reader position is at the end of the file; otherwise, <ph id="ph2">&lt;see langword="false" /&gt;</ph>.</source>
          <target state="translated">판독기 위치가 파일의 끝이면 <ph id="ph1">&lt;see langword="true" /&gt;</ph>이고, 그렇지 않으면 <ph id="ph2">&lt;see langword="false" /&gt;</ph>입니다.</target>       </trans-unit>
        <trans-unit id="131" translate="yes" xml:space="preserve" uid="P:System.Windows.Baml2006.Baml2006Reader.Member">
          <source>Gets the current member at the reader position, if the reader position is on a <ph id="ph1">&lt;see cref="F:System.Xaml.XamlNodeType.StartMember" /&gt;</ph>.</source>
          <target state="translated">판독기 위치가 <ph id="ph1">&lt;see cref="F:System.Xaml.XamlNodeType.StartMember" /&gt;</ph>에 있는 경우 판독기 위치에서 현재 멤버를 가져옵니다.</target>       </trans-unit>
        <trans-unit id="132" translate="yes" xml:space="preserve" extradata="MT" uid="P:System.Windows.Baml2006.Baml2006Reader.Member">
          <source>The current member, or <ph id="ph1">&lt;see langword="null" /&gt;</ph> if the position is not on a member.</source>
          <target state="translated">현재 멤버이거나, 위치가 멤버에 없으면 <ph id="ph1">&lt;see langword="null" /&gt;</ph>입니다.</target>       </trans-unit>
        <trans-unit id="133" translate="yes" xml:space="preserve" uid="P:System.Windows.Baml2006.Baml2006Reader.Namespace">
          <source>Gets the XAML namespace from the current node.</source>
          <target state="translated">현재 노드에서 XAML 네임스페이스를 가져옵니다.</target>       </trans-unit>
        <trans-unit id="134" translate="yes" xml:space="preserve" extradata="MT" uid="P:System.Windows.Baml2006.Baml2006Reader.Namespace">
          <source>The XAML namespace if available, otherwise <ph id="ph1">&lt;see langword="null" /&gt;</ph>.</source>
          <target state="translated">사용할 수 있으면 XAML 네임스페이스이고, 그렇지 않으면 <ph id="ph1">&lt;see langword="null" /&gt;</ph>입니다.</target>       </trans-unit>
        <trans-unit id="135" translate="yes" xml:space="preserve" uid="P:System.Windows.Baml2006.Baml2006Reader.NodeType">
          <source>Gets the type of the current node.</source>
          <target state="translated">현재 노드의 형식을 가져옵니다.</target>       </trans-unit>
        <trans-unit id="136" translate="yes" xml:space="preserve" extradata="MT" uid="P:System.Windows.Baml2006.Baml2006Reader.NodeType">
          <source>A value of the enumeration.</source>
          <target state="translated">열거형 값입니다.</target>       </trans-unit>
        <trans-unit id="137" translate="yes" xml:space="preserve" uid="M:System.Windows.Baml2006.Baml2006Reader.Read">
          <source>Provides the next XAML node from the source BAML, if a node is available.</source>
          <target state="translated">노드를 사용할 수 있는 경우 소스 BAML에서 다음 XAML 노드를 제공합니다.</target>       </trans-unit>
        <trans-unit id="138" translate="yes" xml:space="preserve" uid="M:System.Windows.Baml2006.Baml2006Reader.Read">
          <source><ph id="ph1">&lt;see langword="true" /&gt;</ph> if a node is available; otherwise, <ph id="ph2">&lt;see langword="false" /&gt;</ph>.</source>
          <target state="translated">노드를 사용할 수 있으면 <ph id="ph1">&lt;see langword="true" /&gt;</ph>이고, 그렇지 않으면 <ph id="ph2">&lt;see langword="false" /&gt;</ph>입니다.</target>       </trans-unit>
        <trans-unit id="139" translate="yes" xml:space="preserve" extradata="MT" uid="M:System.Windows.Baml2006.Baml2006Reader.Read">
          <source>This method returns <ph id="ph1">`false`</ph> for cases where the reader reports <ph id="ph2">&lt;xref:System.Windows.Baml2006.Baml2006Reader.IsEof%2A&gt;</ph>.</source>
          <target state="translated">이 메서드가 반환 <ph id="ph1">`false`</ph> 판독기를 보고 하는 경우 <ph id="ph2">&lt;xref:System.Windows.Baml2006.Baml2006Reader.IsEof%2A&gt;</ph>합니다.</target>       </trans-unit>
        <trans-unit id="140" translate="yes" xml:space="preserve" uid="M:System.Windows.Baml2006.Baml2006Reader.Read">
          <source>Reader was disposed during traversal.</source>
          <target state="translated">이동하는 동안 판독기가 삭제되었습니다.</target>       </trans-unit>
        <trans-unit id="141" translate="yes" xml:space="preserve" uid="P:System.Windows.Baml2006.Baml2006Reader.SchemaContext">
          <source>Gets an object that provides schema context information for the information set.</source>
          <target state="translated">정보 집합에 대한 스키마 컨텍스트 정보를 제공하는 개체를 가져옵니다.</target>       </trans-unit>
        <trans-unit id="142" translate="yes" xml:space="preserve" extradata="MT" uid="P:System.Windows.Baml2006.Baml2006Reader.SchemaContext">
          <source>An object that provides schema context information for the information set.</source>
          <target state="translated">정보 집합에 대한 스키마 컨텍스트 정보를 제공하는 개체입니다.</target>       </trans-unit>
        <trans-unit id="143" translate="yes" xml:space="preserve" uid="P:System.Windows.Baml2006.Baml2006Reader.System#Xaml#IXamlLineInfo#HasLineInfo">
          <source>See <ph id="ph1">&lt;see cref="P:System.Xaml.IXamlLineInfo.HasLineInfo" /&gt;</ph>.</source>
          <target state="translated"><ph id="ph1">&lt;see cref="P:System.Xaml.IXamlLineInfo.HasLineInfo" /&gt;</ph>을 참조하세요.</target>       </trans-unit>
        <trans-unit id="144" translate="yes" xml:space="preserve" extradata="MT" uid="P:System.Windows.Baml2006.Baml2006Reader.System#Xaml#IXamlLineInfo#HasLineInfo">
          <source><ph id="ph1">&lt;see langword="true" /&gt;</ph> if line information is available; otherwise, <ph id="ph2">&lt;see langword="false" /&gt;</ph>.</source>
          <target state="translated">줄 정보를 사용할 수 있으면 <ph id="ph1">&lt;see langword="true" /&gt;</ph>이고, 그렇지 않으면 <ph id="ph2">&lt;see langword="false" /&gt;</ph>입니다.</target>       </trans-unit>
        <trans-unit id="145" translate="yes" xml:space="preserve" uid="P:System.Windows.Baml2006.Baml2006Reader.System#Xaml#IXamlLineInfo#LineNumber">
          <source>See <ph id="ph1">&lt;see cref="P:System.Xaml.IXamlLineInfo.LineNumber" /&gt;</ph>.</source>
          <target state="translated"><ph id="ph1">&lt;see cref="P:System.Xaml.IXamlLineInfo.LineNumber" /&gt;</ph>을 참조하세요.</target>       </trans-unit>
        <trans-unit id="146" translate="yes" xml:space="preserve" extradata="MT" uid="P:System.Windows.Baml2006.Baml2006Reader.System#Xaml#IXamlLineInfo#LineNumber">
          <source>The line number to report.</source>
          <target state="translated">보고할 줄 번호입니다.</target>       </trans-unit>
        <trans-unit id="147" translate="yes" xml:space="preserve" uid="P:System.Windows.Baml2006.Baml2006Reader.System#Xaml#IXamlLineInfo#LinePosition">
          <source>See <ph id="ph1">&lt;see cref="P:System.Xaml.IXamlLineInfo.LinePosition" /&gt;</ph>.</source>
          <target state="translated"><ph id="ph1">&lt;see cref="P:System.Xaml.IXamlLineInfo.LinePosition" /&gt;</ph>을 참조하세요.</target>       </trans-unit>
        <trans-unit id="148" translate="yes" xml:space="preserve" extradata="MT" uid="P:System.Windows.Baml2006.Baml2006Reader.System#Xaml#IXamlLineInfo#LinePosition">
          <source>The line position to report.</source>
          <target state="translated">보고할 줄 위치입니다.</target>       </trans-unit>
        <trans-unit id="149" translate="yes" xml:space="preserve" uid="P:System.Windows.Baml2006.Baml2006Reader.Type">
          <source>Gets the <ph id="ph1">&lt;see cref="T:System.Xaml.XamlType" /&gt;</ph> of the current node.</source>
          <target state="translated">현재 노드의 <ph id="ph1">&lt;see cref="T:System.Xaml.XamlType" /&gt;</ph>을 가져옵니다.</target>       </trans-unit>
        <trans-unit id="150" translate="yes" xml:space="preserve" extradata="MT" uid="P:System.Windows.Baml2006.Baml2006Reader.Type">
          <source>The <ph id="ph1">&lt;see cref="T:System.Xaml.XamlType" /&gt;</ph> of the current node, or <ph id="ph2">&lt;see langword="null" /&gt;</ph> if the position is not on an object.</source>
          <target state="translated">현재 노드의 <ph id="ph1">&lt;see cref="T:System.Xaml.XamlType" /&gt;</ph>이거나, 위치가 개체에 없는 경우 <ph id="ph2">&lt;see langword="null" /&gt;</ph>입니다.</target>       </trans-unit>
        <trans-unit id="151" translate="yes" xml:space="preserve" uid="P:System.Windows.Baml2006.Baml2006Reader.Value">
          <source>Gets the value of the current node.</source>
          <target state="translated">현재 노드의 값을 가져옵니다.</target>       </trans-unit>
        <trans-unit id="152" translate="yes" xml:space="preserve" extradata="MT" uid="P:System.Windows.Baml2006.Baml2006Reader.Value">
          <source>The value of the current node, or <ph id="ph1">&lt;see langword="null" /&gt;</ph> if the position is not on a <ph id="ph2">&lt;see cref="F:System.Xaml.XamlNodeType.Value" /&gt;</ph> node type.</source>
          <target state="translated">현재 노드의 값이거나, 위치가 <ph id="ph2">&lt;see cref="F:System.Xaml.XamlNodeType.Value" /&gt;</ph> 노드 형식에 없는 경우 <ph id="ph1">&lt;see langword="null" /&gt;</ph>입니다.</target>       </trans-unit>
      </group>
    </body>
  </file>
</xliff>